mlnlib/mln.py
mlnlib/preparation.py
mlnlib-0.2.39.dist-info/licenses/LICENSE.md
mlnlib-0.2.39.dist-info/METADATA
mlnlib-0.2.39.dist-info/WHEEL
mlnlib-0.2.39.dist-info/top_level.txt
mlnlib-0.2.39.dist-info/RECORD
