Metadata-Version: 2.4
Name: mlnlib
Version: 0.2.39
Summary: Memory-efficient library for loading and working with large unweighted multilayer networks.
Author-email: Eszter Bokányi <e.bokanyi@uva.nl>
Project-URL: Homepage, https://github.com/popnet-io/popnet_mln
Project-URL: Issues, https://github.com/popnet-io/popnet_mln/issues
Classifier: Programming Language :: Python :: 3
Classifier: License :: OSI Approved :: MIT License
Classifier: Operating System :: OS Independent
Requires-Python: >=3.8
License-File: LICENSE.md
Requires-Dist: pandas>=1.4.4
Requires-Dist: polars>=0.20.6
Requires-Dist: numpy>=1.20.3
Requires-Dist: python-igraph>=0.9.9
Requires-Dist: networkx>=3.0
Requires-Dist: scipy>=1.10.1
Dynamic: license-file
